clipShare/__init__.py
clipShare/__main__.py
clipShare/clipShare.py
clipShare/web-interface/__init__.py
clipShare/web-interface/static/images/clipShare.jpeg
clipShare/web-interface/static/images/help.png
clipShare/web-interface/static/js/crypto-js.min.js
clipShare/web-interface/static/js/main.js
clipShare/web-interface/static/js/socket.io.js
clipShare/web-interface/templates/index.html
clipShare-0.1.5.dist-info/LICENSE
clipShare-0.1.5.dist-info/METADATA
clipShare-0.1.5.dist-info/WHEEL
clipShare-0.1.5.dist-info/entry_points.txt
clipShare-0.1.5.dist-info/top_level.txt
clipShare-0.1.5.dist-info/RECORD
