Metadata-Version: 2.1
Name: clipShare
Version: 0.1.5
Summary: Sync clipboard between devices
Home-page: https://github.com/avinashkarhana/clipShare
Author: Avinash Karhana
Author-email: avinashkarhana1@gmail.com
License: LGPLv2.1
Keywords: clipboardSync clipboard sync share encrypted secure clipShare
Classifier: Environment :: Console
Classifier: Environment :: Web Environment
Classifier: Framework :: Flask
Classifier: Intended Audience :: End Users/Desktop
Classifier: License :: OSI Approved :: GNU Lesser General Public License v2 (LGPLv2)
Classifier: Natural Language :: English
Classifier: Operating System :: Microsoft :: Windows :: Windows 10
Classifier: Operating System :: POSIX :: Linux
Classifier: Programming Language :: Python :: 3.8
Classifier: Topic :: Communications
Classifier: Topic :: Internet
Classifier: Topic :: Utilities
Requires-Python: >=3.6
License-File: LICENSE
Requires-Dist: flask
Requires-Dist: Flask-SocketIO
Requires-Dist: python-socketio
Requires-Dist: pyclip
Requires-Dist: pyperclip
Requires-Dist: pycryptodome
Requires-Dist: requests
Requires-Dist: pyngrok
Requires-Dist: netifaces2
Requires-Dist: zeroconf
